openbatch/__init__.py
openbatch/_utils.py
openbatch/collector.py
openbatch/manager.py
openbatch/model.py
openbatch-0.0.3.dist-info/licenses/LICENSE
openbatch-0.0.3.dist-info/METADATA
openbatch-0.0.3.dist-info/WHEEL
openbatch-0.0.3.dist-info/top_level.txt
openbatch-0.0.3.dist-info/RECORD
