Metadata-Version: 2.4
Name: openbatch
Version: 0.0.3
Summary: Create batch jobs for the OpenAI API with ease.
Author-email: Daniel Gomm <daniel.gomm@cwi.nl>
Project-URL: Homepage, https://github.com/daniel-gomm/openbatch
Project-URL: Issues, https://github.com/daniel-gomm/openbatch/issues
Project-URL: Documentation, https://daniel-gomm.github.io/openbatch/
Classifier: Programming Language :: Python :: 3
Classifier: Operating System :: OS Independent
Requires-Python: >=3.5
License-File: LICENSE
Requires-Dist: pydantic>=2.11.9
Dynamic: license-file
